odoo/addons/l10n_br_account_nfe/README.rst
odoo/addons/l10n_br_account_nfe/__init__.py
odoo/addons/l10n_br_account_nfe/__manifest__.py
odoo/addons/l10n_br_account_nfe/demo/account_invoice_demo.xml
odoo/addons/l10n_br_account_nfe/i18n/l10n_br_account_nfe.pot
odoo/addons/l10n_br_account_nfe/models/__init__.py
odoo/addons/l10n_br_account_nfe/models/account_move_line.py
odoo/addons/l10n_br_account_nfe/models/account_payment_mode.py
odoo/addons/l10n_br_account_nfe/models/document_workflow.py
odoo/addons/l10n_br_account_nfe/readme/CONFIGURE.rst
odoo/addons/l10n_br_account_nfe/readme/CONTRIBUTORS.rst
odoo/addons/l10n_br_account_nfe/readme/DESCRIPTION.rst
odoo/addons/l10n_br_account_nfe/readme/HISTORY.rst
odoo/addons/l10n_br_account_nfe/readme/ROADMAP.rst
odoo/addons/l10n_br_account_nfe/readme/USAGE.rst
odoo/addons/l10n_br_account_nfe/static/description/icon.png
odoo/addons/l10n_br_account_nfe/static/description/index.html
odoo/addons/l10n_br_account_nfe/tests/__init__.py
odoo/addons/l10n_br_account_nfe/tests/test_nfe_generate_tags_cobr_dup_pag.py
odoo/addons/l10n_br_account_nfe/views/account_payment_mode.xml
odoo12_addon_l10n_br_account_nfe-12.0.1.2.0.dist-info/METADATA
odoo12_addon_l10n_br_account_nfe-12.0.1.2.0.dist-info/WHEEL
odoo12_addon_l10n_br_account_nfe-12.0.1.2.0.dist-info/top_level.txt
odoo12_addon_l10n_br_account_nfe-12.0.1.2.0.dist-info/RECORD
