Metadata-Version: 2.1
Name: odoo12-addon-l10n-br-account-nfe
Version: 12.0.1.2.0
Summary: Integration between l10n_br_account and l10n_br_nfe
Home-page: https://github.com/OCA/l10n-brazil
Author: Engenere,Akretion,Odoo Community Association (OCA)
Author-email: support@odoo-community.org
License: AGPL-3
Platform: UNKNOWN
Classifier: Programming Language :: Python
Classifier: Framework :: Odoo
Classifier: Framework :: Odoo :: 12.0
Classifier: License :: OSI Approved :: GNU Affero General Public License v3
Classifier: Development Status :: 3 - Alpha
Requires-Python: >=3.5
Requires-Dist: odoo12-addon-account-payment-partner
Requires-Dist: odoo12-addon-l10n-br-account
Requires-Dist: odoo12-addon-l10n-br-nfe
Requires-Dist: odoo (<12.1dev,>=12.0a)
